mecs/__init__.py
mecs/__main__.py
mecs/mecs.py
mecs/test_mecs.py
py_mecs-0.1.1.dist-info/LICENSE.txt
py_mecs-0.1.1.dist-info/METADATA
py_mecs-0.1.1.dist-info/WHEEL
py_mecs-0.1.1.dist-info/top_level.txt
py_mecs-0.1.1.dist-info/RECORD
